pythondata_cpu_cv32e40p/__init__.py
pythondata_cpu_cv32e40p/system_verilog/.dir-locals.el
pythondata_cpu_cv32e40p/system_verilog/.gitignore
pythondata_cpu_cv32e40p/system_verilog/.gitlab-ci.yml
pythondata_cpu_cv32e40p/system_verilog/.gitmodules
pythondata_cpu_cv32e40p/system_verilog/.readthedocs.yaml
pythondata_cpu_cv32e40p/system_verilog/.travis.yml
pythondata_cpu_cv32e40p/system_verilog/Bender.yml
pythondata_cpu_cv32e40p/system_verilog/CITATION.cff
pythondata_cpu_cv32e40p/system_verilog/CONTRIBUTING.md
pythondata_cpu_cv32e40p/system_verilog/LICENSE
pythondata_cpu_cv32e40p/system_verilog/README.md
pythondata_cpu_cv32e40p/system_verilog/cv32e40p_dm_manifest.flist
pythondata_cpu_cv32e40p/system_verilog/cv32e40p_fpu_manifest.flist
pythondata_cpu_cv32e40p/system_verilog/cv32e40p_manifest.flist
pythondata_cpu_cv32e40p/system_verilog/cv32e40p_trace_manifest.flist
pythondata_cpu_cv32e40p/system_verilog/python-requirements.txt
pythondata_cpu_cv32e40p/system_verilog/src_files.yml
pythondata_cpu_cv32e40p/system_verilog/.github/release.yml
pythondata_cpu_cv32e40p/system_verilog/.github/ISSUE_TEMPLATE/bug.md
pythondata_cpu_cv32e40p/system_verilog/.github/ISSUE_TEMPLATE/config.yml
pythondata_cpu_cv32e40p/system_verilog/.github/ISSUE_TEMPLATE/enhancement.md
pythondata_cpu_cv32e40p/system_verilog/.github/ISSUE_TEMPLATE/question.md
pythondata_cpu_cv32e40p/system_verilog/.github/ISSUE_TEMPLATE/task.md
pythondata_cpu_cv32e40p/system_verilog/.github/workflows/aws.yml
pythondata_cpu_cv32e40p/system_verilog/.github/workflows/aws_cv32e40p.md
pythondata_cpu_cv32e40p/system_verilog/.github/workflows/check_target_on_pr.yml
pythondata_cpu_cv32e40p/system_verilog/.github/workflows/lint.yml
pythondata_cpu_cv32e40p/system_verilog/.github/workflows/merge_dev_to_master.yml
pythondata_cpu_cv32e40p/system_verilog/bhv/cv32e40p_apu_tracer.sv
pythondata_cpu_cv32e40p/system_verilog/bhv/cv32e40p_core_log.sv
pythondata_cpu_cv32e40p/system_verilog/bhv/cv32e40p_instr_trace.svh
pythondata_cpu_cv32e40p-1.0.1.post1909.dist-info/LICENSE
pythondata_cpu_cv32e40p-1.0.1.post1909.dist-info/METADATA
pythondata_cpu_cv32e40p-1.0.1.post1909.dist-info/WHEEL
pythondata_cpu_cv32e40p-1.0.1.post1909.dist-info/top_level.txt
pythondata_cpu_cv32e40p-1.0.1.post1909.dist-info/RECORD
