Metadata-Version: 2.2
Name: pythondata-cpu-cv32e40p
Version: 1.0.1.post1909
Summary: Python module containing system_verilog files for CV32E40P cpu.
Home-page: https://github.com/litex-hub/pythondata-cpu-cv32e40p
Author: LiteX Authors
Author-email: litex@googlegroups.com
Project-URL: Bug Tracker, https://github.com/litex-hub/pythondata-cpu-cv32e40p/issues
Project-URL: Source Code, https://github.com/litex-hub/pythondata-cpu-cv32e40p
Classifier: Programming Language :: Python :: 3
Classifier: License :: OSI Approved :: Apache Software License
Classifier: Operating System :: OS Independent
Requires-Python: >=3.5
License-File: LICENSE
Dynamic: author
Dynamic: author-email
Dynamic: classifier
Dynamic: description
Dynamic: description-content-type
Dynamic: home-page
Dynamic: project-url
Dynamic: requires-python
Dynamic: summary
